README.md
setup.py
src/har2tavern/__init__.py
src/har2tavern/main.py
src/har2tavern.egg-info/PKG-INFO
src/har2tavern.egg-info/SOURCES.txt
src/har2tavern.egg-info/dependency_links.txt
src/har2tavern.egg-info/entry_points.txt
src/har2tavern.egg-info/requires.txt
src/har2tavern.egg-info/top_level.txt