Metadata-Version: 2.1
Name: har2tavern
Version: 0.0.1
Summary: Generate yaml test cese from HAR file
Home-page: https://github.com/dongfangtianyu/har2tavern
Author: dongfangtianyu
License: UNKNOWN
Platform: UNKNOWN
Requires-Python: >=3.7
